{"gtabs":[{"panes":[{"ptabs":[{"history":[{"dir":"/home/ocean/.config","file":"vifm","relpos":7,"ts":1662888034},{"dir":"/home/ocean","file":".dwm","relpos":3,"ts":1662888034},{"dir":"/home/ocean/.dwm","file":"..","relpos":0,"ts":1662888034},{"dir":"/home/ocean","file":".config","relpos":2,"ts":1662888034},{"dir":"/home/ocean/.config","file":"vifm","relpos":7,"ts":1662888034},{"dir":"/home/ocean","file":".config","relpos":2,"ts":1662888034},{"dir":"/home/ocean/.config","file":"vifm","relpos":7,"ts":1662888034},{"dir":"/home/ocean","file":".dwm","relpos":3,"ts":1662888034},{"dir":"/home/ocean/.dwm","file":"..","relpos":0,"ts":1662888034},{"dir":"/home/ocean","file":".oh-my-zsh","relpos":6,"ts":1662888034},{"dir":"/home/ocean/.config/vifm","file":"vifmrc","relpos":7,"ts":1662889979},{"dir":"/home/ocean/.config","file":"vifm","relpos":7,"ts":1662893511},{"dir":"/home/ocean/.config/vifm","file":"vifminfo.json","relpos":6,"ts":1662893511},{"dir":"/home/ocean/.config","file":"vifm","relpos":7,"ts":1662893511},{"dir":"/home/ocean/.config/vifm","file":"vifminfo.json","relpos":6,"ts":1662893511},{"dir":"/home/ocean/.config","file":"vifm","relpos":7,"ts":1662893511},{"dir":"/home/ocean/.config/vifm","file":"vifminfo.json","relpos":6,"ts":1662893511},{"dir":"/home/ocean/.config","file":"vifm","relpos":7,"ts":1662893511},{"dir":"/home/ocean/.config/vifm","file":"vifminfo.json","relpos":6,"ts":1662893511},{"dir":"/home/ocean/.config","file":"neofetch","relpos":5,"ts":1662951214},{"dir":"/home/ocean","file":"Downloads","relpos":9,"ts":1662951214},{"dir":"/home/ocean/.config","file":"neofetch","relpos":5,"ts":1662951214},{"dir":"/home/ocean","file":"Downloads","relpos":9,"ts":1662951214},{"dir":"/home/ocean/.config/vifm","file":"scripts","relpos":3,"ts":1662955430},{"dir":"/home/ocean/.config","file":"vifm","relpos":7,"ts":1662981377},{"dir":"/home/ocean/.config/vifm","file":"scripts","relpos":3,"ts":1662981377},{"dir":"/home/ocean/.config","file":"vifm","relpos":7,"ts":1662981377},{"dir":"/home/ocean/.config/vifm","file":"scripts","relpos":3,"ts":1662981377},{"dir":"/home/ocean/.config","file":"neofetch","relpos":5,"ts":1662981528},{"dir":"/home/ocean","file":"Downloads","relpos":9,"ts":1662981528},{"dir":"/home","file":"ocean","relpos":1,"ts":1662981528},{"dir":"/","file":"etc","relpos":3,"ts":1662981528},{"dir":"/etc","file":"xdg","relpos":25,"ts":1662981528},{"dir":"/home/ocean/.config","file":"neofetch","relpos":5,"ts":1662981528},{"dir":"/home/ocean","file":"Downloads","relpos":9,"ts":1662981528},{"dir":"/home","file":"ocean","relpos":1,"ts":1662981528},{"dir":"/","file":"etc","relpos":3,"ts":1662981528},{"dir":"/etc","file":"xdg","relpos":25,"ts":1662981528},{"dir":"/etc/xdg","file":"picom.conf","relpos":5,"ts":1662983371},{"dir":"/etc","file":"xdg","relpos":25,"ts":1662984920},{"dir":"/","file":"home","relpos":4,"ts":1662984920},{"dir":"/home/ocean","file":"Downloads","relpos":9,"ts":1662984920},{"dir":"/etc","file":"xdg","relpos":25,"ts":1662984920},{"dir":"/","file":"home","relpos":4,"ts":1662984920},{"dir":"/home/ocean","file":"Downloads","relpos":9,"ts":1662984920},{"dir":"/home/ocean/Downloads","file":"..","relpos":0,"ts":1662985161},{"dir":"/home/ocean","file":"Downloads","relpos":9,"ts":1662985161},{"dir":"/home/ocean/Downloads","file":"..","relpos":0,"ts":1662985161},{"dir":"/home/ocean","file":".ssh","relpos":8,"ts":1662985161},{"dir":"/home/ocean/.ssh","file":"id_rsa","relpos":1,"ts":1662985161},{"dir":"/home/ocean/Downloads","file":"..","relpos":0,"ts":1662985161},{"dir":"/home/ocean","file":"Downloads","relpos":9,"ts":1662985161},{"dir":"/home/ocean/Downloads","file":"..","relpos":0,"ts":1662985161},{"dir":"/home/ocean","file":".ssh","relpos":8,"ts":1662985161},{"dir":"/home/ocean/.ssh","file":"id_rsa","relpos":1,"ts":1662985161},{"dir":"/home/ocean","file":"Downloads","relpos":9,"ts":1662985315},{"dir":"/home","file":"ocean","relpos":1,"ts":1662985315},{"dir":"/","file":"lib64","relpos":6,"ts":1662985315},{"dir":"/home/ocean","file":"Downloads","relpos":9,"ts":1662985315},{"dir":"/home","file":"ocean","relpos":1,"ts":1662985315},{"dir":"/","file":"lib64","relpos":6,"ts":1662985315},{"dir":"/home/ocean","file":"Downloads","relpos":9,"ts":1662985363},{"dir":"/","file":"home","relpos":4,"ts":1662985418},{"dir":"/home/ocean","file":"Downloads","relpos":9,"ts":1662985418},{"dir":"/","file":"home","relpos":4,"ts":1662985418},{"dir":"/home/ocean","file":"Downloads","relpos":9,"ts":1662985418},{"dir":"/home","file":"ocean","relpos":1,"ts":1662985523},{"dir":"/","file":"home","relpos":4,"ts":1662985523},{"dir":"/home","file":"ocean","relpos":1,"ts":1662985523},{"dir":"/","file":"home","relpos":4,"ts":1662985523},{"dir":"/home","file":"ocean","relpos":1,"ts":1662985523},{"dir":"/home/ocean","file":"dwm","relpos":11,"ts":1662985523},{"dir":"/home","file":"ocean","relpos":1,"ts":1662985523},{"dir":"/","file":"home","relpos":4,"ts":1662985523},{"dir":"/home","file":"ocean","relpos":1,"ts":1662985523},{"dir":"/","file":"home","relpos":4,"ts":1662985523},{"dir":"/home","file":"ocean","relpos":1,"ts":1662985523},{"dir":"/home/ocean","file":"dwm","relpos":11,"ts":1662985523},{"dir":"/home","file":"don","relpos":1,"ts":1684999639},{"dir":"/","file":"home","relpos":4,"ts":1684999639},{"dir":"/home","file":"don","relpos":1,"ts":1684999639},{"dir":"/","file":"home","relpos":4,"ts":1684999639},{"dir":"/home/don","file":"Desktop","relpos":6,"ts":1685806708},{"dir":"/home/don/Desktop","file":"steam++","relpos":1,"ts":1685806708},{"dir":"/home/don/Desktop/steam++","file":"Steam++.ico","relpos":3,"ts":1685806708},{"dir":"/home/don/Desktop","file":"..","relpos":0,"ts":1685806708},{"dir":"/home/don","file":"Desktop","relpos":6,"ts":1685806708},{"dir":"/home/don/Desktop","file":"steam++","relpos":1,"ts":1685806708},{"dir":"/home/don/Desktop/steam++","file":"Steam++.ico","relpos":3,"ts":1685806708},{"dir":"/home/don/Desktop","file":"..","relpos":0,"ts":1685806708},{"dir":"/home/don","file":"Pictures","relpos":17,"ts":1685806708},{"dir":"/home/don/Pictures","file":"..","relpos":0,"ts":1685810972},{"dir":"/home/don","file":"Pictures","relpos":17,"ts":1685811526},{"dir":"/home/don/Pictures","file":"ArcoLinux-2023-06-04-1685810986_screenshot_1920x1080.jpg","relpos":1,"ts":1685811526},{"dir":"/home/don","file":"Pictures","relpos":17,"ts":1685811526},{"dir":"/home/don/Pictures","file":"ArcoLinux-2023-06-04-1685810986_screenshot_1920x1080.jpg","relpos":1,"ts":1685811526},{"dir":"/home/don","file":"Documents","relpos":14,"ts":1685814966},{"dir":"/home/don/Documents","file":"1.docx","relpos":3,"ts":1685814966},{"dir":"/home/don","file":"Documents","relpos":14,"ts":1685814966},{"dir":"/home/don/Documents","file":"1.docx","relpos":3,"ts":1685814966}],"filters":{"invert":true,"dot":false,"manual":"","auto":""},"last-location":"/home/don/Documents","sorting":[2],"preview":true}]},{"ptabs":[{"history":[{"dir":"/home/ocean","file":"..","relpos":0,"ts":1662955430},{"dir":"/home","file":"ocean","relpos":1,"ts":1662955430},{"dir":"/home/ocean","file":"..","relpos":0,"ts":1662955430},{"dir":"/home","file":"ocean","relpos":1,"ts":1662955430},{"dir":"/home/ocean","file":"..","relpos":0,"ts":1662955430},{"dir":"/home","file":"ocean","relpos":1,"ts":1662955430},{"dir":"/home/ocean","file":"..","relpos":0,"ts":1662955430},{"dir":"/home","file":"ocean","relpos":1,"ts":1662955430},{"dir":"/home/ocean","file":"..","relpos":0,"ts":1662955430},{"dir":"/home","file":"ocean","relpos":1,"ts":1662955430},{"dir":"/home/ocean","file":"..","relpos":0,"ts":1662955430},{"dir":"/home","file":"ocean","relpos":1,"ts":1662955430},{"dir":"/home/ocean","file":"..","relpos":0,"ts":1662955430},{"dir":"/home","file":"ocean","relpos":1,"ts":1662955430},{"dir":"/home/ocean","file":"..","relpos":0,"ts":1662955430},{"dir":"/home","file":"ocean","relpos":1,"ts":1662955430},{"dir":"/home/ocean","file":"..","relpos":0,"ts":1662955430},{"dir":"/home","file":"ocean","relpos":1,"ts":1662955430},{"dir":"/home/ocean","file":"..","relpos":0,"ts":1662955430},{"dir":"/home","file":"ocean","relpos":1,"ts":1662955430},{"dir":"/home/ocean","file":"..","relpos":0,"ts":1662955430},{"dir":"/home","file":"ocean","relpos":1,"ts":1662955430},{"dir":"/home/ocean","file":"..","relpos":0,"ts":1662955430},{"dir":"/home","file":"ocean","relpos":1,"ts":1662955430},{"dir":"/home/ocean","file":"..","relpos":0,"ts":1662955430},{"dir":"/home","file":"ocean","relpos":1,"ts":1662955430},{"dir":"/home/ocean","file":"..","relpos":0,"ts":1662955430},{"dir":"/home","file":"ocean","relpos":1,"ts":1662955430},{"dir":"/home/ocean","file":"..","relpos":0,"ts":1662955430},{"dir":"/home","file":"ocean","relpos":1,"ts":1662955430},{"dir":"/home/ocean","file":"..","relpos":0,"ts":1662955430},{"dir":"/home","file":"ocean","relpos":1,"ts":1662955430},{"dir":"/home/ocean","file":"..","relpos":0,"ts":1662955430},{"dir":"/home","file":"ocean","relpos":1,"ts":1662955430},{"dir":"/home/ocean","file":"..","relpos":0,"ts":1662955430},{"dir":"/home","file":"ocean","relpos":1,"ts":1662955430},{"dir":"/home/ocean","file":"..","relpos":0,"ts":1662955430},{"dir":"/home","file":"ocean","relpos":1,"ts":1662955430},{"dir":"/home/ocean","file":"..","relpos":0,"ts":1662955430},{"dir":"/home","file":"ocean","relpos":1,"ts":1662955430},{"dir":"/home/ocean","file":"..","relpos":0,"ts":1662955430},{"dir":"/home","file":"ocean","relpos":1,"ts":1662955430},{"dir":"/home/ocean","file":"..","relpos":0,"ts":1662955430},{"dir":"/home","file":"ocean","relpos":1,"ts":1662955430},{"dir":"/home/ocean","file":"..","relpos":0,"ts":1662955430},{"dir":"/home","file":"ocean","relpos":1,"ts":1662955430},{"dir":"/home/ocean","file":"..","relpos":0,"ts":1662955430},{"dir":"/home","file":"ocean","relpos":1,"ts":1662955430},{"dir":"/home/ocean","file":"..","relpos":0,"ts":1662955430},{"dir":"/home","file":"ocean","relpos":1,"ts":1662955430},{"dir":"/home/ocean","file":"..","relpos":0,"ts":1662955430},{"dir":"/home","file":"ocean","relpos":1,"ts":1662955430},{"dir":"/home/ocean","file":"..","relpos":0,"ts":1662955430},{"dir":"/home","file":"ocean","relpos":1,"ts":1662955430},{"dir":"/home/ocean","file":"..","relpos":0,"ts":1662955430},{"dir":"/home","file":"ocean","relpos":1,"ts":1662955430},{"dir":"/home/ocean","file":"..","relpos":0,"ts":1662955430},{"dir":"/home","file":"ocean","relpos":1,"ts":1662955430},{"dir":"/home/ocean","file":"..","relpos":0,"ts":1662955430},{"dir":"/home","file":"ocean","relpos":1,"ts":1662955430},{"dir":"/home/ocean","file":"..","relpos":0,"ts":1662955430},{"dir":"/home","file":"ocean","relpos":1,"ts":1662955430},{"dir":"/home/ocean","file":"..","relpos":0,"ts":1662955430},{"dir":"/home","file":"ocean","relpos":1,"ts":1662955430},{"dir":"/home/ocean","file":"..","relpos":0,"ts":1662955430},{"dir":"/home","file":"ocean","relpos":1,"ts":1662955430},{"dir":"/home/ocean","file":"..","relpos":0,"ts":1662955430},{"dir":"/home","file":"ocean","relpos":1,"ts":1662955430},{"dir":"/home/ocean","file":"..","relpos":0,"ts":1662955430},{"dir":"/home","file":"ocean","relpos":1,"ts":1662955430},{"dir":"/home/ocean","file":"..","relpos":0,"ts":1662955430},{"dir":"/home","file":"ocean","relpos":1,"ts":1662955430},{"dir":"/home/ocean","file":"..","relpos":0,"ts":1662955430},{"dir":"/home","file":"ocean","relpos":1,"ts":1662955430},{"dir":"/home/ocean","file":"..","relpos":0,"ts":1662955430},{"dir":"/home","file":"ocean","relpos":1,"ts":1662955430},{"dir":"/home/ocean","file":"..","relpos":0,"ts":1662955430},{"dir":"/home","file":"ocean","relpos":1,"ts":1662955430},{"dir":"/home/ocean","file":"..","relpos":0,"ts":1662955430},{"dir":"/home","file":"ocean","relpos":1,"ts":1662955430},{"dir":"/home/ocean","file":"..","relpos":0,"ts":1662955430},{"dir":"/home","file":"ocean","relpos":1,"ts":1662955430},{"dir":"/home/ocean","file":"..","relpos":0,"ts":1662955430},{"dir":"/home","file":"ocean","relpos":1,"ts":1662955430},{"dir":"/home/ocean","file":"..","relpos":0,"ts":1662955430},{"dir":"/home","file":"ocean","relpos":1,"ts":1662955430},{"dir":"/home/ocean","file":"..","relpos":0,"ts":1662955430},{"dir":"/home","file":"ocean","relpos":1,"ts":1662955430},{"dir":"/home/ocean","file":"..","relpos":0,"ts":1662955430},{"dir":"/home","file":"ocean","relpos":1,"ts":1662955430},{"dir":"/home/ocean","file":"..","relpos":0,"ts":1662955430},{"dir":"/home","file":"ocean","relpos":1,"ts":1662955430},{"dir":"/home/ocean","file":"..","relpos":0,"ts":1662955430},{"dir":"/home","file":"ocean","relpos":1,"ts":1662955430},{"dir":"/home/ocean","file":"..","relpos":0,"ts":1662955430},{"dir":"/home","file":"ocean","relpos":1,"ts":1662955430},{"dir":"/home/ocean","file":"..","relpos":0,"ts":1662955430},{"dir":"/home","file":"ocean","relpos":1,"ts":1662955430},{"dir":"/home/ocean","file":"..","relpos":0,"ts":1662955430},{"dir":"/home","file":"","relpos":0,"ts":1684999639}],"filters":{"invert":true,"dot":true,"manual":"","auto":""},"last-location":"/home","sorting":[2],"preview":true}]}],"active-pane":0,"preview":true,"splitter":{"pos":-1,"ratio":0.5,"orientation":"v","expanded":false}}],"marks":{"H":{"dir":"/home/ocean/","file":"..","ts":1662873313},"b":{"dir":"/home/don/bin/","file":"..","ts":1684999632},"h":{"dir":"/home/don/","file":"..","ts":1684999632},"k":{"dir":"/home/ocean/.config/vifm","file":"vifmrc","ts":1662955414},"z":{"dir":"/home/ocean/.config/vifm","file":"..","ts":1662873313}},"bmarks":{},"cmd-hist":[{"text":"FZF","ts":1662878401},{"text":"fzf","ts":1662878401},{"text":"session","ts":1662879884},{"text":"s","ts":1662879884},{"text":"colorscheme","ts":1662879884},{"text":"cd","ts":1662888034},{"text":"cd ","ts":1662888034},{"text":"df","ts":1662888440},{"text":"cd .config/vifm/","ts":1662889979},{"text":"cd ~","ts":1662984920},{"text":"cd $HOME","ts":1662985363}],"search-hist":[{"text":".conf","ts":1662873668},{"text":".con","ts":1662873668},{"text":"c","ts":1662889979}],"prompt-hist":[{"text":"gruvbox.vifm","ts":1662875881}],"regs":{},"dir-stack":[],"use-term-multiplexer":false}